LICENSE
MANIFEST.in
README.md
setup.py
ha_graphapi.egg-info/PKG-INFO
ha_graphapi.egg-info/SOURCES.txt
ha_graphapi.egg-info/dependency_links.txt
ha_graphapi.egg-info/requires.txt
ha_graphapi.egg-info/top_level.txt
hagraph/api/__init__.py
hagraph/api/client.py
hagraph/api/auth/__init__.py
hagraph/api/auth/manager.py
hagraph/api/auth/models.py
hagraph/api/provider/__init__.py
hagraph/api/provider/baseprovider.py
hagraph/api/provider/presence/__init__.py
hagraph/api/provider/presence/models.py