Metadata-Version: 1.1
Name: ha-graphapi
Version: 0.0.18
Summary: For use with Home Assistant to query Microsoft's Graph API
Home-page: https://github.com/jlweston/ha-graphapi/
Author: Jamie Weston
Author-email: UNKNOWN
License: MIT
Platform: UNKNOWN
Classifier: Development Status :: 4 - Beta
Classifier: Intended Audience :: Developers
Classifier: License :: OSI Approved :: MIT License
Classifier: Programming Language :: Python :: 3
Classifier: Programming Language :: Python :: 3.6
Classifier: Programming Language :: Python :: 3.7
Classifier: Programming Language :: Python :: 3.8
